Metadata-Version: 1.0
Name: licensetool
Version: 0.0.5
Summary: 设备指纹获取、license生成、指纹与有效期验证工具
Home-page: https://github.com/gm19900510/licensetool
Author: gm
Author-email: 1025304567@qq.com
License: MIT Licence
Keywords: pip,license,licensetool,tool,gm
Platform: any
